setup.py
salint/__init__.py
salint/__main__.py
salint/parser.py
salint/script.py
salint.egg-info/PKG-INFO
salint.egg-info/SOURCES.txt
salint.egg-info/dependency_links.txt
salint.egg-info/entry_points.txt
salint.egg-info/top_level.txt
salint/rules/__init__.py
salint/rules/args.py
salint/rules/requisites.py
salint/rules/yaml.py