Metadata-Version: 1.1
Name: salint
Version: 0.0.2
Summary: Linter for SaltStack States
Home-page: https://github.com/gtmanfred/salint
Author: Daniel Wallace
Author-email: daniel@saltstack.com
License: UNKNOWN
Project-URL: Bug Reports, https://github.com/gtmanfred/salint/issues
Project-URL: Source, https://github.com/gtmanfred/salint/
Platform: UNKNOWN
Classifier: Development Status :: 3 - Alpha
Classifier: Topic :: Software Development :: Build Tools
Classifier: License :: OSI Approved :: Apache Software License
Classifier: Environment :: Console
Classifier: Intended Audience :: Developers
Classifier: Intended Audience :: Information Technology
Classifier: Intended Audience :: System Administrators
Classifier: Programming Language :: Python :: 2.7
Classifier: Programming Language :: Python :: 3.4
Classifier: Programming Language :: Python :: 3.5
Classifier: Programming Language :: Python :: 3.6
Classifier: Programming Language :: Python :: 3.7
